pyomnisci/__init__.py
pyomnisci/_loaders.py
pyomnisci/_mutators.py
pyomnisci/_pandas_loaders.py
pyomnisci/_transforms.py
pyomnisci/_utils.py
pyomnisci/_version.py
pyomnisci/connection.py
pyomnisci/ipc.py
pyomnisci-0.28.2.dist-info/LICENSE.md
pyomnisci-0.28.2.dist-info/METADATA
pyomnisci-0.28.2.dist-info/WHEEL
pyomnisci-0.28.2.dist-info/top_level.txt
pyomnisci-0.28.2.dist-info/RECORD
